federated_content_connector/__init__.py
federated_content_connector/apps.py
federated_content_connector/constants.py
federated_content_connector/course_metadata_importer.py
federated_content_connector/models.py
federated_content_connector/signals.py
federated_content_connector/tasks.py
federated_content_connector/urls.py
federated_content_connector/filters/__init__.py
federated_content_connector/filters/pipeline.py
federated_content_connector/management/__init__.py
federated_content_connector/management/commands/__init__.py
federated_content_connector/management/commands/import_course_runs_metadata.py
federated_content_connector/management/commands/refresh_course_runs_metadata.py
federated_content_connector/migrations/0001_initial.py
federated_content_connector/migrations/0002_coursedetailsimportstatus.py
federated_content_connector/migrations/0003_reset_refresh_timestamp.py
federated_content_connector/migrations/0004_coursedetails_course_key.py
federated_content_connector/migrations/0005_auto_20250314_0537.py
federated_content_connector/migrations/__init__.py
federated_content_connector/settings/__init__.py
federated_content_connector/settings/common.py
federated_content_connector/settings/production.py
federated_content_connector/templates/federated_content_connector/base.html
federated_content_connector-1.7.0.dist-info/LICENSE.txt
federated_content_connector-1.7.0.dist-info/METADATA
federated_content_connector-1.7.0.dist-info/WHEEL
federated_content_connector-1.7.0.dist-info/entry_points.txt
federated_content_connector-1.7.0.dist-info/top_level.txt
federated_content_connector-1.7.0.dist-info/RECORD
