Metadata-Version: 2.1
Name: federated-content-connector
Version: 1.7.0
Summary: One-line description for README and other doc files.
Home-page: https://github.com/openedx/federated-content-connector
Author: edX
Author-email: oscm@edx.org
License: AGPL 3.0
Keywords: Python edx
Classifier: Development Status :: 3 - Alpha
Classifier: Framework :: Django
Classifier: Framework :: Django :: 3.2
Classifier: Intended Audience :: Developers
Classifier: License :: OSI Approved :: GNU Affero General Public License v3 or later (AGPLv3+)
Classifier: Natural Language :: English
Classifier: Programming Language :: Python :: 3
Classifier: Programming Language :: Python :: 3.8
Requires-Python: >=3.8
License-File: LICENSE.txt
Requires-Dist: Django
Requires-Dist: backoff
Requires-Dist: celery
Requires-Dist: django-extensions
Requires-Dist: edx-django-utils
Requires-Dist: edx-opaque-keys
Requires-Dist: openedx-filters
